whoisrecon/__init__.py
whoisrecon/utils.py
whoisrecon/whoisrecon.py
whoisrecon-0.1.2.dist-info/LICENSE
whoisrecon-0.1.2.dist-info/METADATA
whoisrecon-0.1.2.dist-info/WHEEL
whoisrecon-0.1.2.dist-info/entry_points.txt
whoisrecon-0.1.2.dist-info/top_level.txt
whoisrecon-0.1.2.dist-info/RECORD
