Metadata-Version: 2.1
Name: whoisrecon
Version: 0.1.2
Summary: WHOIS Reconnaissance Tool
Home-page: https://www.github.com/MythicStack/whoisrecon
Author: John Christian (MythicStack)
Maintainer: John Christian (MythicStack)
Maintainer-email: mythicstack@pm.me
License: Apache License 2.0
Platform: Unix
Platform: Windows
Classifier: Programming Language :: Python :: 3
Classifier: License :: OSI Approved :: Apache Software License
Classifier: Operating System :: OS Independent
Requires-Python: >=3
License-File: LICENSE
Requires-Dist: setuptools
Requires-Dist: argparse
Requires-Dist: tabulate
Requires-Dist: requests
Requires-Dist: whois
Requires-Dist: bs4
